thunder/__init__.py
thunder/auth.py
thunder/config.py
thunder/get_latest.py
thunder/thunder.py
thunder/utils.py
thunder/test/__init__.py
thunder/test/tests/__init__.py
thunder/test/tests/conftest.py
thunder/test/tests/test_authentication.py
thunder/test/tests/test_create.py
thunder/test/tests/test_delete.py
thunder/test/tests/test_device.py
thunder/test/tests/test_run.py
thunder/test/tests/test_start.py
thunder/test/tests/test_status.py
thunder/test/tests/test_stop.py
tnr-1.7.31.dist-info/METADATA
tnr-1.7.31.dist-info/WHEEL
tnr-1.7.31.dist-info/entry_points.txt
tnr-1.7.31.dist-info/licenses/LICENSE
tnr-1.7.31.dist-info/RECORD
