Metadata-Version: 2.4
Name: tnr
Version: 1.7.31
Summary: Thunder Compute CLI
Author-email: Thunder Compute <support@thundercompute.com>
License: Elastic License 2.0
License-File: LICENSE
Classifier: Development Status :: 5 - Production/Stable
Classifier: Environment :: Console
Classifier: Intended Audience :: Developers
Classifier: Operating System :: OS Independent
Classifier: Programming Language :: Python :: 3
Classifier: Programming Language :: Python :: 3.7
Classifier: Programming Language :: Python :: 3.8
Classifier: Programming Language :: Python :: 3.9
Classifier: Programming Language :: Python :: 3.10
Classifier: Programming Language :: Python :: 3.11
Requires-Python: >=3.7
Requires-Dist: aiohttp>=3.11.18
Requires-Dist: click<8.2.0
Requires-Dist: cryptography>=40.0
Requires-Dist: importlib-metadata>=4.0.0; python_version < '3.8'
Requires-Dist: packaging>=21.0
Requires-Dist: paramiko==3.4.0
Requires-Dist: pywin32==308; platform_system == 'Windows'
Requires-Dist: questionary==2.1.1
Requires-Dist: requests>=2.2
Requires-Dist: rich-click==1.8.3
Requires-Dist: rich==13.7.1
Requires-Dist: scp==0.15.0
Requires-Dist: sentry-sdk==2.20.0
